machine/__init__.py
machine/core.py
machine/settings.py
machine/bin/__init__.py
machine/bin/run.py
machine/clients/__init__.py
machine/clients/slack.py
machine/handlers/__init__.py
machine/handlers/command_handler.py
machine/handlers/event_handler.py
machine/handlers/interactive_handler.py
machine/handlers/logging.py
machine/handlers/message_handler.py
machine/models/__init__.py
machine/models/channel.py
machine/models/core.py
machine/models/interactive.py
machine/models/user.py
machine/plugins/__init__.py
machine/plugins/admin_utils.py
machine/plugins/base.py
machine/plugins/block_action.py
machine/plugins/command.py
machine/plugins/decorators.py
machine/plugins/message.py
machine/plugins/metadata.py
machine/plugins/modals.py
machine/plugins/builtin/__init__.py
machine/plugins/builtin/admin.py
machine/plugins/builtin/debug.py
machine/plugins/builtin/general.py
machine/plugins/builtin/help.py
machine/plugins/builtin/fun/__init__.py
machine/plugins/builtin/fun/images.py
machine/plugins/builtin/fun/memes.py
machine/plugins/builtin/fun/regexes.py
machine/storage/__init__.py
machine/storage/backends/__init__.py
machine/storage/backends/base.py
machine/storage/backends/dynamodb.py
machine/storage/backends/memory.py
machine/storage/backends/redis.py
machine/storage/backends/sqlite.py
machine/utils/__init__.py
machine/utils/collections.py
machine/utils/datetime.py
machine/utils/logging.py
machine/utils/module_loading.py
machine/utils/redis.py
slack_machine-0.40.1.dist-info/METADATA
slack_machine-0.40.1.dist-info/WHEEL
slack_machine-0.40.1.dist-info/entry_points.txt
slack_machine-0.40.1.dist-info/licenses/AUTHORS
slack_machine-0.40.1.dist-info/licenses/LICENSE
slack_machine-0.40.1.dist-info/RECORD
