Metadata-Version: 2.4
Name: slack-machine
Version: 0.40.1
Summary: A wonderful, simple, yet powerful and extendable Slack bot framework
Project-URL: homepage, https://github.com/DonDebonair/slack-machine
Project-URL: repository, https://github.com/DonDebonair/slack-machine
Project-URL: documentation, https://DonDebonair.github.io/slack-machine/
Author-email: Daan Debie <daan@dv.email>
License: MIT License
License-File: AUTHORS
License-File: LICENSE
Classifier: Development Status :: 4 - Beta
Classifier: Intended Audience :: Developers
Classifier: License :: OSI Approved :: MIT License
Classifier: Natural Language :: English
Classifier: Operating System :: OS Independent
Classifier: Programming Language :: Python :: 3 :: Only
Classifier: Programming Language :: Python :: 3.9
Classifier: Programming Language :: Python :: 3.10
Classifier: Programming Language :: Python :: 3.11
Classifier: Programming Language :: Python :: 3.12
Classifier: Programming Language :: Python :: 3.13
Classifier: Topic :: Communications :: Chat
Classifier: Topic :: Internet
Classifier: Topic :: Office/Business
Requires-Python: <4.0,>=3.9
Requires-Dist: aiohttp<4.0.0,>=3.8.5
Requires-Dist: apscheduler<4.0.0,>=3.9.1
Requires-Dist: dill<1.0.0.0,>=0.3.5.1
Requires-Dist: httpx<0.29,>=0.28
Requires-Dist: multidict<7.0.0,>=6.0.5
Requires-Dist: pydantic<3.0.0,>=2.2.1
Requires-Dist: pyee<13.1.0,>=13.0.0
Requires-Dist: slack-sdk<4.0.0,>=3.18.1
Requires-Dist: structlog<25.5,>=25.4
Requires-Dist: tzdata<2025.3,>=2025.2
Provides-Extra: dynamodb
Requires-Dist: aioboto3<16,>=15; extra == 'dynamodb'
Provides-Extra: redis
Requires-Dist: hiredis<4,>=2; extra == 'redis'
Requires-Dist: redis<6.5.0,>=6.4.0; extra == 'redis'
Provides-Extra: sqlite
Requires-Dist: aiosqlite<0.22,>=0.21; extra == 'sqlite'
